wfaccountmanager/__init__.py
wfaccountmanager-0.0.7.dist-info/LICENSE
wfaccountmanager-0.0.7.dist-info/METADATA
wfaccountmanager-0.0.7.dist-info/WHEEL
wfaccountmanager-0.0.7.dist-info/top_level.txt
wfaccountmanager-0.0.7.dist-info/RECORD
